README.txt
setup.py
collective/__init__.py
collective.portlettabber.egg-info/PKG-INFO
collective.portlettabber.egg-info/SOURCES.txt
collective.portlettabber.egg-info/dependency_links.txt
collective.portlettabber.egg-info/entry_points.txt
collective.portlettabber.egg-info/namespace_packages.txt
collective.portlettabber.egg-info/not-zip-safe
collective.portlettabber.egg-info/paster_plugins.txt
collective.portlettabber.egg-info/requires.txt
collective.portlettabber.egg-info/top_level.txt
collective/portlettabber/__init__.py
collective/portlettabber/configure.zcml
collective/portlettabber/tests.py
collective/portlettabber/browser/__init__.py
collective/portlettabber/browser/configure.zcml
collective/portlettabber/browser/jquery.portlettabber.js
collective/portlettabber/browser/portlet_tabber.css
collective/portlettabber/profiles/default/cssregistry.xml
collective/portlettabber/profiles/default/jsregistry.xml
collective/portlettabber/profiles/default/metadata.xml
docs/HISTORY.txt
docs/INSTALL.txt
docs/LICENSE.GPL
docs/LICENSE.txt