Metadata-Version: 1.0
Name: collective.portlettabber
Version: 0.1.0
Summary: A jQuery plugin for Plone layouts that merge portlets together obtaining a single portlet with tabs
Home-page: http://plone.org/products/collective.portlettabber
Author: RedTurtle Technology
Author-email: sviluppoplone@redturtle.net
License: GPL
Keywords: plone tab portlet jquery
Platform: UNKNOWN
Classifier: Framework :: Plone
Classifier: Programming Language :: Python
Classifier: Programming Language :: JavaScript
Classifier: Development Status :: 4 - Beta
Classifier: Topic :: Software Development :: User Interfaces
